{"errors":[],"warnings":[],"namedChunkGroups":{"app":{"chunks":[4,1,0],"assets":["webpack-runtime-13e995832090e53b7f58.js","webpack-runtime-13e995832090e53b7f58.js.map","commons-4c726a275f5c2e74ff77.js","commons-4c726a275f5c2e74ff77.js.map","app-cec8df528fd05aac24f2.js","app-cec8df528fd05aac24f2.js.map"],"children":{},"childAssets":{}},"component---src-pages-index-js":{"chunks":[3,2],"assets":["styles.9ff60710add96dce31f8.css","styles-12aa67b167babcc8ef69.js","styles-12aa67b167babcc8ef69.js.map","component---src-pages-index-js-ae43afc21c82fa3fbd3e.js","component---src-pages-index-js-ae43afc21c82fa3fbd3e.js.map"],"children":{},"childAssets":{}}},"assetsByChunkName":{"app":["webpack-runtime-13e995832090e53b7f58.js","commons-4c726a275f5c2e74ff77.js","app-cec8df528fd05aac24f2.js"],"component---src-pages-index-js":["styles.9ff60710add96dce31f8.css","styles-12aa67b167babcc8ef69.js","component---src-pages-index-js-ae43afc21c82fa3fbd3e.js"]}}